common_client_scheduler/__init__.py
common_client_scheduler/config.py
common_client_scheduler/exceptions.py
common_client_scheduler/headers.py
common_client_scheduler/helper.py
common_client_scheduler/protobuf/client_scheduler_messages.proto
common_client_scheduler/protobuf/generate_protobuf.md
common_client_scheduler/protobuf/generated/client_scheduler_messages_pb2.py
common_client_scheduler/protobuf/generated/client_scheduler_messages_pb2.pyi
common_client_scheduler/py.typed
common_client_scheduler/read_top_level_functions.py
common_client_scheduler/requests.py
common_client_scheduler/responses.py
common_client_scheduler/structs.py
terality/__init__.py
terality/__main__.py
terality/_terality/__init__.py
terality/_terality/_testing/__init__.py
terality/_terality/_testing/config.py
terality/_terality/_testing/data_transfers.py
terality/_terality/bin/__main__.py
terality/_terality/caching.py
terality/_terality/client.py
terality/_terality/constants.py
terality/_terality/data_transfers/__init__.py
terality/_terality/data_transfers/azure.py
terality/_terality/data_transfers/local.py
terality/_terality/data_transfers/s3.py
terality/_terality/data_transmitter.py
terality/_terality/encoding/__init__.py
terality/_terality/encoding/decoder.py
terality/_terality/encoding/encoder.py
terality/_terality/errorreporting.py
terality/_terality/globals.py
terality/_terality/httptransport.py
terality/_terality/options.py
terality/_terality/patch_libs/__init__.py
terality/_terality/patch_libs/patch_pandas_and_numpy.py
terality/_terality/patch_libs/plot/__init__.py
terality/_terality/patch_libs/plot/patch_hist.py
terality/_terality/patch_libs/plot/plot_accessor.py
terality/_terality/patch_libs/seaborn_/__init__.py
terality/_terality/patch_libs/seaborn_/patch_boxplot.py
terality/_terality/progress_bar.py
terality/_terality/replay.py
terality/_terality/sentry.py
terality/_terality/terality_structures/__init__.py
terality/_terality/terality_structures/common.py
terality/_vendor/single_source-0.2.0.dist-info/INSTALLER
terality/_vendor/single_source-0.2.0.dist-info/LICENSE
terality/_vendor/single_source-0.2.0.dist-info/METADATA
terality/_vendor/single_source-0.2.0.dist-info/RECORD
terality/_vendor/single_source-0.2.0.dist-info/REQUESTED
terality/_vendor/single_source-0.2.0.dist-info/WHEEL
terality/_vendor/single_source-0.2.0.dist-info/top_level.txt
terality_serde/_vendor/cloudpickle-2.0.0.dist-info/INSTALLER
terality_serde/_vendor/cloudpickle-2.0.0.dist-info/LICENSE
terality_serde/_vendor/cloudpickle-2.0.0.dist-info/METADATA
terality_serde/_vendor/cloudpickle-2.0.0.dist-info/RECORD
terality_serde/_vendor/cloudpickle-2.0.0.dist-info/REQUESTED
terality_serde/_vendor/cloudpickle-2.0.0.dist-info/WHEEL
terality_serde/_vendor/cloudpickle-2.0.0.dist-info/top_level.txt
terality-0.14.21.dist-info/entry_points.txt
terality-0.14.21.dist-info/WHEEL
terality-0.14.21.dist-info/METADATA
terality-0.14.21.dist-info/RECORD
