Metadata-Version: 2.1
Name: terality
Version: 0.14.21
Summary: The Data Processing Engine for Data Scientists
Home-page: https://terality.com/
License: Proprietary
Author: Terality Engineering Team
Author-email: dev.null@terality.com
Requires-Python: >=3.7.1,<4.0.0
Classifier: License :: Other/Proprietary License
Classifier: Programming Language :: Python :: 3
Classifier: Programming Language :: Python :: 3.10
Classifier: Programming Language :: Python :: 3.8
Classifier: Programming Language :: Python :: 3.9
Provides-Extra: azure
Requires-Dist: azure-identity (>=1.6.0,<2.0.0); extra == "azure"
Requires-Dist: azure-storage-blob (>=12.8.1,<13.0.0); extra == "azure"
Requires-Dist: azure-storage-file-datalake (>=12.4.0,<13.0.0); extra == "azure"
Requires-Dist: boto3 (>=1.16.28)
Requires-Dist: click (>=3.2,<9)
Requires-Dist: importlib_metadata (>=3.0,<5); python_version < "3.8"
Requires-Dist: numpy (>=1.18,<2.0)
Requires-Dist: pandas (>=1.0.0,<2.0.0)
Requires-Dist: protobuf (>=3.9.1,<4.0.0)
Requires-Dist: pyarrow (>=6.0.0,<7.0.0)
Requires-Dist: pydantic (>=1.7.3,<2.0.0)
Requires-Dist: requests (>=2.23.0,<3.0.0)
Requires-Dist: sentry-sdk (>=1.3.0,<2.0.0)
Requires-Dist: tqdm (>=4.45.0,<5.0.0)
